sunkit_instruments/__init__.py
sunkit_instruments/_version.py
sunkit_instruments/conftest.py
sunkit_instruments/utils.py
sunkit_instruments/version.py
sunkit_instruments/data/README.rst
sunkit_instruments/data/__init__.py
sunkit_instruments/data/test/__init__.py
sunkit_instruments/data/test/annotation_lyra.db
sunkit_instruments/data/test/annotation_manual.db
sunkit_instruments/data/test/annotation_ppt.db
sunkit_instruments/data/test/annotation_science.db
sunkit_instruments/data/test/go1520110607.fits
sunkit_instruments/data/test/goes_15_test_chianti_tem_idl.sav
sunkit_instruments/data/test/goes_16_test_chianti_tem_idl.sav
sunkit_instruments/data/test/hsi_calib_ev_20020220_1106_20020220_1106_25_40.fits
sunkit_instruments/data/test/hsi_image_20101016_191218.fits
sunkit_instruments/data/test/hsi_imagecube_clean_20150930_1307_1tx1e.fits
sunkit_instruments/data/test/hsi_imagecube_clean_20151214_2255_2tx2e.fits
sunkit_instruments/data/test/hsi_obssumm_20110404_042.fits.gz
sunkit_instruments/data/test/hsi_obssumm_20120601_018_truncated.fits.gz
sunkit_instruments/data/test/hsi_obssumm_filedb_201104.txt
sunkit_instruments/data/test/iris_l2_20130801_074720_4040000014_SJI_1400_t000.fits
sunkit_instruments/data/test/lyra_20150101-000000_lev3_std_truncated.fits.gz
sunkit_instruments/data/test/sci_gxrs-l2-irrad_g15_d20170910_v0-0-0_truncated.nc
sunkit_instruments/data/test/sci_xrsf-l2-flx1s_g16_d20170910_v2-1-0_truncated.nc
sunkit_instruments/data/test/sci_xrsf-l2-flx1s_g18_d20250328_v2-2-0_truncated.nc
sunkit_instruments/fermi/__init__.py
sunkit_instruments/fermi/fermi.py
sunkit_instruments/fermi/tests/__init__.py
sunkit_instruments/fermi/tests/test_fermi.py
sunkit_instruments/goes_xrs/__init__.py
sunkit_instruments/goes_xrs/goes_chianti_tem.py
sunkit_instruments/goes_xrs/goes_xrs.py
sunkit_instruments/goes_xrs/tests/__init__.py
sunkit_instruments/goes_xrs/tests/test_goes_xrs.py
sunkit_instruments/iris/__init__.py
sunkit_instruments/iris/iris.py
sunkit_instruments-0.6.2.dist-info/licenses/LICENSE.rst
sunkit_instruments-0.6.2.dist-info/METADATA
sunkit_instruments-0.6.2.dist-info/WHEEL
sunkit_instruments-0.6.2.dist-info/top_level.txt
sunkit_instruments-0.6.2.dist-info/RECORD
