Metadata-Version: 2.4
Name: sunkit_instruments
Version: 0.6.2
Summary: A SunPy-affiliated package for solar instruments
Author-email: The SunPy Community <sunpy@googlegroups.com>
License: Copyright (c) 2024, The SunPy Community
Project-URL: Homepage, https://sunpy.org
Project-URL: Source Code, https://github.com/sunpy/sunkit-instruments
Project-URL: Download, https://pypi.org/project/sunkit-instruments
Project-URL: Documentation, https://docs.sunpy.org/projects/sunkit-instruments
Project-URL: Changelog, https://docs.sunpy.org/projects/sunkit-instruments/en/stable/whatsnew/changelog.html
Project-URL: Issue Tracker, https://github.com/sunpy/sunkit-instruments/issues
Requires-Python: >=3.10
License-File: LICENSE.rst
Requires-Dist: sunpy[map,net,timeseries,visualization]>=6.0.0
Requires-Dist: xarray>=2023.12.0
Requires-Dist: astropy>=5.3.0
Requires-Dist: packaging>=23.0
Requires-Dist: scipy!=1.10.0,>=1.9.0
Requires-Dist: numpy>=1.23.5
Requires-Dist: h5py>=3.7.0
Requires-Dist: matplotlib>=3.6.0
Requires-Dist: pandas>=1.4.0
Provides-Extra: tests
Requires-Dist: pytest; extra == "tests"
Requires-Dist: pytest-astropy; extra == "tests"
Requires-Dist: pytest-doctestplus; extra == "tests"
Requires-Dist: pytest-cov; extra == "tests"
Requires-Dist: pytest-xdist; extra == "tests"
Provides-Extra: docs
Requires-Dist: sphinx; extra == "docs"
Requires-Dist: sphinx-automodapi; extra == "docs"
Requires-Dist: sphinx-changelog; extra == "docs"
Requires-Dist: sunpy-sphinx-theme; extra == "docs"
Requires-Dist: packaging; extra == "docs"
Requires-Dist: sphinx-gallery; extra == "docs"
Dynamic: license-file
